meetups.py
meetups-0.0.29.data/data/etc/meetups/readme.md
meetups-0.0.29.data/data/etc/meetups/version
meetups-0.0.29.dist-info/DESCRIPTION.rst
meetups-0.0.29.dist-info/METADATA
meetups-0.0.29.dist-info/RECORD
meetups-0.0.29.dist-info/WHEEL
meetups-0.0.29.dist-info/entry_points.txt
meetups-0.0.29.dist-info/metadata.json
meetups-0.0.29.dist-info/top_level.txt
